{
  "words": [
    {
      "word": "algorithm",
      "pronunciation": "/ˈælɡərɪðəm/",
      "partOfSpeech": "noun",
      "definition": "A set of rules or instructions that a computer follows to solve a problem or perform a task.",
      "indonesian": "algoritma",
      "level": "B2",
      "ieltsBand": "7.0",
      "example": "The search engine uses a complex algorithm to rank websites.",
      "collocations": [
        "complex algorithm",
        "search algorithm",
        "learning algorithm",
        "data algorithm",
        "algorithm design"
      ],
      "synonyms": [
        "procedure",
        "process",
        "method",
        "formula"
      ]
    },
    {
      "word": "automation",
      "pronunciation": "/ˌɔːtəˈmeɪʃən/",
      "partOfSpeech": "noun",
      "definition": "The use of technology to carry out a task with minimal human intervention.",
      "indonesian": "otomatisasi",
      "level": "B2",
      "ieltsBand": "7.0",
      "example": "Automation in manufacturing has led to increased efficiency.",
      "collocations": [
        "industrial automation",
        "process automation",
        "office automation",
        "automation system",
        "degree of automation"
      ],
      "synonyms": [
        "mechanization",
        "robotics",
        "self-operation"
      ]
    },
    {
      "word": "deployment",
      "pronunciation": "/dɪˈplɔɪmənt/",
      "partOfSpeech": "noun",
      "definition": "The act of bringing resources, such as technology or personnel, into effective action.",
      "indonesian": "penerapan",
      "level": "B2",
      "ieltsBand": "7.0",
      "example": "The deployment of the new AI system will take several months.",
      "collocations": [
        "software deployment",
        "system deployment",
        "full deployment",
        "successful deployment",
        "deployment strategy"
      ],
      "synonyms": [
        "implementation",
        "application",
        "rollout",
        "installation"
      ]
    },
    {
      "word": "neural network",
      "pronunciation": "/ˈnjʊərəl ˈnɛtwɜːk/",
      "partOfSpeech": "noun",
      "definition": "A computational model inspired by the structure and function of the human brain, used in machine learning.",
      "indonesian": "jaringan saraf tiruan",
      "level": "C1",
      "ieltsBand": "7.0",
      "example": "Deep learning models often utilize complex neural networks.",
      "collocations": [
        "deep neural network",
        "artificial neural network",
        "convolutional neural network",
        "recurrent neural network",
        "train a neural network"
      ],
      "synonyms": [
        "ANN",
        "computational network"
      ]
    },
    {
      "word": "predictive",
      "pronunciation": "/prɪˈdɪktɪv/",
      "partOfSpeech": "adjective",
      "definition": "Able to foretell or forecast future events or outcomes.",
      "indonesian": "prediktif",
      "level": "B2",
      "ieltsBand": "7.0",
      "example": "Predictive analytics can help businesses anticipate market trends.",
      "collocations": [
        "predictive modeling",
        "predictive maintenance",
        "predictive analytics",
        "predictive capabilities",
        "predictive power"
      ],
      "synonyms": [
        "forecasting",
        "prophetic",
        "prescient"
      ]
    },
    {
      "word": "scalability",
      "pronunciation": "/ˌskeɪləˈbɪləti/",
      "partOfSpeech": "noun",
      "definition": "The ability of a system or technology to handle a growing amount of work, or its potential to be enlarged to accommodate that growth.",
      "indonesian": "skalabilitas",
      "level": "C1",
      "ieltsBand": "7.5",
      "example": "The cloud infrastructure offers excellent scalability for our growing user base.",
      "collocations": [
        "system scalability",
        "application scalability",
        "high scalability",
        "ensure scalability",
        "scalability issues"
      ],
      "synonyms": [
        "expandability",
        "flexibility",
        "adaptability"
      ]
    },
    {
      "word": "supervised learning",
      "pronunciation": "/ˈsuːpərvaɪzd ˈlɜːrnɪŋ/",
      "partOfSpeech": "noun phrase",
      "definition": "A type of machine learning where an algorithm learns from a labeled dataset, meaning each training example has a known output.",
      "indonesian": "pembelajaran terawasi",
      "level": "C1",
      "ieltsBand": "7.5",
      "example": "Supervised learning is commonly used for classification and regression tasks.",
      "collocations": [
        "supervised learning algorithm",
        "supervised learning model",
        "supervised learning technique",
        "supervised learning task",
        "supervised learning data"
      ],
      "synonyms": [
        "labeled learning"
      ]
    },
    {
      "word": "unsupervised learning",
      "pronunciation": "/ʌnˈsuːpərvaɪzd ˈlɜːrnɪŋ/",
      "partOfSpeech": "noun phrase",
      "definition": "A type of machine learning where an algorithm learns from unlabeled data, identifying patterns and structures on its own.",
      "indonesian": "pembelajaran tak terawasi",
      "level": "C1",
      "ieltsBand": "7.5",
      "example": "Unsupervised learning is useful for discovering hidden patterns in large datasets.",
      "collocations": [
        "unsupervised learning algorithm",
        "unsupervised learning model",
        "unsupervised learning task",
        "unsupervised learning data",
        "unsupervised learning method"
      ],
      "synonyms": [
        "unlabeled learning"
      ]
    }
  ]
}